presamples/__init__.py
presamples/array.py
presamples/campaigns.py
presamples/errors.py
presamples/fallbacks.py
presamples/indexer.py
presamples/loader.py
presamples/package_interface.py
presamples/packaging.py
presamples/utils.py
presamples/models/__init__.py
presamples/models/fixed_sum.py
presamples/models/inventory_base.py
presamples/models/kronecker_delta.py
presamples/models/model_base.py
presamples/models/parameterized.py
presamples-0.2.7.dist-info/LICENSE
presamples-0.2.7.dist-info/METADATA
presamples-0.2.7.dist-info/WHEEL
presamples-0.2.7.dist-info/top_level.txt
presamples-0.2.7.dist-info/RECORD
