Metadata-Version: 2.1
Name: presamples
Version: 0.2.7
Summary: Package to write, load, manage and verify numerical arrays, called presamples.
Home-page: https://github.com/PascalLesage/presamples
Author: Pascal Lesage
Author-email: pascal.lesage@polymtl.ca
License: UNKNOWN
Platform: UNKNOWN
Classifier: Intended Audience :: End Users/Desktop
Classifier: Intended Audience :: Developers
Classifier: Intended Audience :: Science/Research
Classifier: License :: OSI Approved :: BSD License
Classifier: Operating System :: MacOS :: MacOS X
Classifier: Operating System :: Microsoft :: Windows
Classifier: Operating System :: POSIX
Classifier: Programming Language :: Python
Classifier: Programming Language :: Python :: 3
Classifier: Programming Language :: Python :: 3.4
Classifier: Programming Language :: Python :: 3.5
Classifier: Programming Language :: Python :: 3.6
Classifier: Programming Language :: Python :: 3.7
Classifier: Programming Language :: Python :: 3.8
Classifier: Topic :: Scientific/Engineering :: Information Analysis
Classifier: Topic :: Scientific/Engineering :: Mathematics
Requires-Dist: bw2calc
Requires-Dist: bw2data
Requires-Dist: numpy
Requires-Dist: peewee
Requires-Dist: scipy
Requires-Dist: stats-arrays
Requires-Dist: wrapt
